python_package_13630/__init__.py
python_package_13630/calculation.py
python_package_13630-0.0.1.dist-info/METADATA
python_package_13630-0.0.1.dist-info/WHEEL
python_package_13630-0.0.1.dist-info/top_level.txt
python_package_13630-0.0.1.dist-info/RECORD
