Metadata-Version: 2.2
Name: python_package_13630
Version: 0.0.1
Summary: A test python package for class assignment
Dynamic: description
Dynamic: description-content-type
Dynamic: summary
